setup.py
tjueweb/__init__.py
tjueweb/client.py
tjueweb/format.py
tjueweb/handy.py
tjueweb/httputils.py
tjueweb/pattern.py
tjueweb.egg-info/PKG-INFO
tjueweb.egg-info/SOURCES.txt
tjueweb.egg-info/dependency_links.txt
tjueweb.egg-info/requires.txt
tjueweb.egg-info/top_level.txt