Metadata-Version: 1.0
Name: tjueweb
Version: 0.0.1
Summary: A client library for e.tju.edu.cn (tju-eweb)
Home-page: https://github.com/tesseract2048/tju-eweb
Author: tess3ract
Author-email: hty0807@gmail.com
License: GNU GENERAL PUBLIC LICENSE
